fwminer/__init__.py
fwminer/fwminer.py
fwminer-0.0.1.dist-info/LICENSE
fwminer-0.0.1.dist-info/METADATA
fwminer-0.0.1.dist-info/WHEEL
fwminer-0.0.1.dist-info/top_level.txt
fwminer-0.0.1.dist-info/RECORD
